e2c/__init__.py
e2c/actors/__init__.py
e2c/actors/analyser.py
e2c/actors/graph.py
e2c/actors/loader.py
e2c/actors/parser.py
e2c/actors/resolve.py
e2c/actors/visualizer.py
e2c/actors/async/__init__.py
e2c/actors/async/graph.py
e2c/async/__init__.py
e2c/contracts/__init__.py
e2c/contracts/actor.py
e2c/contracts/const.py
e2c/contracts/errors.py
e2c/contracts/event.py
e2c/contracts/async/__init__.py
e2c/contracts/async/actor.py
e2c/contracts/async/event.py
e2c/integrations/__init__.py
e2c/integrations/graph.py
e2c/integrations/async/__init__.py
e2c/integrations/async/graph.py
e2c-0.46.2.dist-info/METADATA
e2c-0.46.2.dist-info/RECORD
e2c-0.46.2.dist-info/WHEEL
e2c-0.46.2.dist-info/top_level.txt
tests/__init__.py
tests/actors/__init__.py
tests/actors/test_analyser.py
tests/actors/test_graph.py
tests/actors/test_loader.py
tests/actors/test_parser.py
tests/actors/test_resolve.py
tests/actors/test_visualizer.py
tests/actors/async/__init__.py
tests/actors/async/test_graph.py
tests/contracts/__init__.py
tests/contracts/test_actor.py
tests/contracts/test_event.py
tests/contracts/async/__init__.py
tests/contracts/async/test_actor.py
tests/contracts/async/test_event.py
tests/integrations/__init__.py
tests/integrations/test_graph.py
