Metadata-Version: 2.1
Name: e2c
Version: 0.46.2
Summary: Elastic Event Components is an open source software library to build flexible architectures using dataflow graphs.
Home-page: http://e2c.readthedocs.io
Author: E2c Authors
Author-email: stefan.bergmann@enterstry.com
License: Apache 2.0
Project-URL: Bug Reports, https://gitlab.com/elastic-event-components/e2c/issues
Project-URL: Source, https://gitlab.com/elastic-event-components/e2c
Keywords: architecture dataflow dotnet e2c flow graph python
Platform: any
Classifier: Development Status :: 5 - Production/Stable
Classifier: Intended Audience :: Developers
Classifier: Topic :: Software Development :: Libraries
Classifier: License :: OSI Approved :: Apache Software License
Classifier: Programming Language :: Python :: 3.6
Requires-Python: >=3.6
Requires-Dist: twine
Requires-Dist: pytest
Requires-Dist: pytest-cov
Requires-Dist: pytest-asyncio
